cross_objects/__init__.py
cross_objects/elrs.py
cross_objects/sections.py
cross_objects-0.1.1.dist-info/METADATA
cross_objects-0.1.1.dist-info/WHEEL
cross_objects-0.1.1.dist-info/RECORD
